gymdash/__init__.py
gymdash/start.py
gymdash/backend/__init__.py
gymdash/backend/constants.py
gymdash/backend/enums.py
gymdash/backend/main.py
gymdash/backend/project.py
gymdash/backend/core/__init__.py
gymdash/backend/core/api/__init__.py
gymdash/backend/core/api/models.py
gymdash/backend/core/api/stream.py
gymdash/backend/core/api/config/__init__.py
gymdash/backend/core/api/config/config.py
gymdash/backend/core/api/config/stat_tags.py
gymdash/backend/core/patch/__init__.py
gymdash/backend/core/patch/patcher.py
gymdash/backend/core/patch/tensorboard_extensions.py
gymdash/backend/core/simulation/__init__.py
gymdash/backend/core/simulation/base.py
gymdash/backend/core/simulation/callbacks.py
gymdash/backend/core/simulation/examples.py
gymdash/backend/core/simulation/export.py
gymdash/backend/core/simulation/manage.py
gymdash/backend/core/utils/__init__.py
gymdash/backend/core/utils/file_format.py
gymdash/backend/core/utils/json.py
gymdash/backend/core/utils/kwarg_utils.py
gymdash/backend/core/utils/state.py
gymdash/backend/core/utils/thread_utils.py
gymdash/backend/core/utils/type_utils.py
gymdash/backend/core/utils/usage.py
gymdash/backend/core/utils/zip.py
gymdash/backend/exported_args/args.pickle
gymdash/backend/gymnasium/__init__.py
gymdash/backend/gymnasium/utils/__init__.py
gymdash/backend/gymnasium/utils/wrapper_utils.py
gymdash/backend/gymnasium/wrappers/MediaFileStatLinker.py
gymdash/backend/gymnasium/wrappers/RecordVideoCustom.py
gymdash/backend/gymnasium/wrappers/RecordVideoToTensorboard.py
gymdash/backend/gymnasium/wrappers/StreamWrapper.py
gymdash/backend/gymnasium/wrappers/TensorboardStreamWrapper.py
gymdash/backend/gymnasium/wrappers/__init__.py
gymdash/backend/stable_baselines/__init__.py
gymdash/backend/stable_baselines/callbacks.py
gymdash/backend/tensorboard/MediaLinkStreamableStat.py
gymdash/backend/tensorboard/TensorboardStreamableStat.py
gymdash/backend/tensorboard/__init__.py
gymdash/backend/torch/__init__.py
gymdash/backend/torch/base.py
gymdash-0.1.4.dist-info/licenses/LICENSE
gymdash-0.1.4.dist-info/METADATA
gymdash-0.1.4.dist-info/WHEEL
gymdash-0.1.4.dist-info/top_level.txt
gymdash-0.1.4.dist-info/RECORD
