Metadata-Version: 2.4
Name: gymdash
Version: 0.1.4
Summary: A simulation dashboard for keeping track of, analyzing, and interacting with simulations and reinforcement learning projects.
Author-email: Chase Vickery <chasedvickery@gmail.com>
License-Expression: MIT
Project-URL: Homepage, https://github.com/ChaseDVickery/GymDash
Project-URL: Issues, https://github.com/ChaseDVickery/GymDash/issues
Classifier: Programming Language :: Python :: 3
Classifier: Operating System :: OS Independent
Requires-Python: >=3.9
License-File: LICENSE
Requires-Dist: fastapi>=0.115.0
Requires-Dist: uvicorn[standard]>=0.34.0
Requires-Dist: gputil>=1.4.0
Requires-Dist: psutil>=7.0.0
Requires-Dist: pandas>=2.2.3
Requires-Dist: pydantic>=2.11.3
Requires-Dist: matplotlib>=3.9.4
Requires-Dist: box2d
Requires-Dist: tensorboard>=2
Provides-Extra: full
Requires-Dist: gymnasium[classic-control]>=1.1.1; extra == "full"
Requires-Dist: moviepy==1.0.3; extra == "full"
Requires-Dist: stable_baselines3[extra]>=2.6.0; extra == "full"
Dynamic: license-file
